pysymphony/__init__.py
pysymphony/client.py
pysymphony/constants.py
pysymphony/runs.py
pysymphony/settings.py
pysymphony/tooling.py
pysymphony/utils.py
pysymphony/workflows.py
pysymphony-0.2.4.dist-info/METADATA
pysymphony-0.2.4.dist-info/WHEEL
pysymphony-0.2.4.dist-info/top_level.txt
pysymphony-0.2.4.dist-info/RECORD
