Metadata-Version: 2.1
Name: pysymphony
Version: 0.2.4
Summary: A Python client for Symphony
Home-page: https://github.com/compositionlabs/pysymphony
Author: Chinmay Shrivastava
Author-email: cshrivastava99@gmail.com
Classifier: Programming Language :: Python :: 3
Classifier: License :: OSI Approved :: MIT License
Classifier: Operating System :: OS Independent
Requires-Python: >=3.10
Requires-Dist: certifi ==2024.8.30
Requires-Dist: charset-normalizer ==3.3.2
Requires-Dist: idna ==3.10
Requires-Dist: requests ==2.32.3
Requires-Dist: urllib3 ==2.2.3
